gatherunique/__init__.py
gatherunique-0.1.0.dist-info/LICENSE
gatherunique-0.1.0.dist-info/METADATA
gatherunique-0.1.0.dist-info/WHEEL
gatherunique-0.1.0.dist-info/top_level.txt
gatherunique-0.1.0.dist-info/RECORD
