Metadata-Version: 2.1
Name: gatherunique
Version: 0.1.0
Summary: Simple, unique list gatherer, with *args for passable blacklist check and optional list_in for automated sorting against blacklist/s
Home-page: https://github.com/dpazavalos/datatypes/tree/master/gatherunique
Author: Daniel Paz Avalos
Author-email: dpazavalos@protonmail.com
License: UNKNOWN
Platform: UNKNOWN
Classifier: Programming Language :: Python :: 3
Classifier: License :: OSI Approved :: MIT License
Classifier: Operating System :: OS Independent
